pagerduty2splunk/__init__.py
pagerduty2splunk/main.py
pagerduty2splunk-0.0.1.dist-info/DESCRIPTION.rst
pagerduty2splunk-0.0.1.dist-info/METADATA
pagerduty2splunk-0.0.1.dist-info/RECORD
pagerduty2splunk-0.0.1.dist-info/WHEEL
pagerduty2splunk-0.0.1.dist-info/entry_points.txt
pagerduty2splunk-0.0.1.dist-info/metadata.json
pagerduty2splunk-0.0.1.dist-info/top_level.txt
