Metadata-Version: 2.0
Name: pagerduty2splunk
Version: 0.0.1
Summary: A tool for pushing PagerDuty logs to Splunk
Home-page: https://github.com/Sam-Martin/PagerDuty2Splunk
Author: Sam Martin
Author-email: samjackmartin@gmail.com
License: Apache 2.0
Keywords: pagerduty splunk
Platform: UNKNOWN
Classifier: Development Status :: 3 - Alpha
Classifier: Intended Audience :: Administrators
Classifier: Topic :: ETL :: ETL Tools
Classifier: License :: OSI Approved :: Apache 2.0 License
Classifier: Programming Language :: Python :: 2
Classifier: Programming Language :: Python :: 2.6
Classifier: Programming Language :: Python :: 2.7
Classifier: Programming Language :: Python :: 3
Classifier: Programming Language :: Python :: 3.3
Classifier: Programming Language :: Python :: 3.4
Classifier: Programming Language :: Python :: 3.5
